README.rst
setup.py
BitcoinValueGraph/__init__.py
BitcoinValueGraph/bitcoin_value_graph.py
BitcoinValueGraph.egg-info/PKG-INFO
BitcoinValueGraph.egg-info/SOURCES.txt
BitcoinValueGraph.egg-info/dependency_links.txt
BitcoinValueGraph.egg-info/entry_points.txt
BitcoinValueGraph.egg-info/requires.txt
BitcoinValueGraph.egg-info/top_level.txt