Metadata-Version: 1.0
Name: BitcoinValueGraph
Version: 0.6
Summary: Bitcoin value
Home-page: https://github.com/Urosh91/Bitcoin-Value
Author: Uroš Jevremović
Author-email: jevremovic.uros91@gmail.com
License: UNKNOWN
Platform: UNKNOWN
